setup.py
tests/__init__.py
tests/test_memorytracker.py
tests/test_redistracker.py
tests/utils.py
tgext/__init__.py
tgext.asyncjob.egg-info/PKG-INFO
tgext.asyncjob.egg-info/SOURCES.txt
tgext.asyncjob.egg-info/dependency_links.txt
tgext.asyncjob.egg-info/entry_points.txt
tgext.asyncjob.egg-info/namespace_packages.txt
tgext.asyncjob.egg-info/not-zip-safe
tgext.asyncjob.egg-info/requires.txt
tgext.asyncjob.egg-info/top_level.txt
tgext/asyncjob/__init__.py
tgext/asyncjob/progress.py
tgext/asyncjob/queue.py
tgext/asyncjob/sqlahelpers.py
tgext/asyncjob/tghooks.py
tgext/asyncjob/worker.py
tgext/asyncjob/trackers/__init__.py
tgext/asyncjob/trackers/memory.py
tgext/asyncjob/trackers/redisdb.py