Metadata-Version: 1.1
Name: tgext.asyncjob
Version: 0.3.1
Summary: Asynchronous jobs worker for TurboGears2
Home-page: http://bitbucket.org/axant/tgext.asyncjob
Author: Alessandro Molina
Author-email: alessandro.molina@axant.it
License: MIT
Keywords: turbogears2.extension pylons
Platform: UNKNOWN
Classifier: Environment :: Web Environment
Classifier: Topic :: Software Development :: Libraries :: Python Modules
Classifier: Framework :: TurboGears
